qt4_gengui/__init__.py
qt4_gengui/_version.py
qt4_gengui/build_gui.py
qt4_gengui/config_file.py
qt4_gengui/excel_const.py
qt4_gengui/generic_dialog.py
qt4_gengui/gui_main.py
qt4_gengui/recent_files.py
qt4_gengui/xlChFormula.py
qt4_gengui/xlChart.py
qt4_gengui/examples/a_tow.dat
qt4_gengui/examples/chk_dialog.py
qt4_gengui/examples/chk_gui.py
qt4_gengui/examples/example_1.py
qt4_gengui/html/index.html
qt4_gengui/images/document.png
qt4_gengui/images/excel.jpg
qt4_gengui/images/exit.jpg
qt4_gengui/images/help.jpg
qt4_gengui/images/new.jpg
qt4_gengui/images/open.jpg
qt4_gengui/images/powerpoint.jpg
qt4_gengui/images/print.png
qt4_gengui/images/run.jpg
qt4_gengui/images/save.jpg
qt4_gengui/images/save_v2.jpg
qt4_gengui/images/save_v3.jpg
qt4_gengui/images/save_v4.jpg
qt4_gengui/images/saveas.jpg
qt4_gengui/tests/__init__.py
qt4_gengui/tests/test_qt4_gengui.py
qt4_gengui-0.0.1.dist-info/DESCRIPTION.rst
qt4_gengui-0.0.1.dist-info/METADATA
qt4_gengui-0.0.1.dist-info/RECORD
qt4_gengui-0.0.1.dist-info/WHEEL
qt4_gengui-0.0.1.dist-info/entry_points.txt
qt4_gengui-0.0.1.dist-info/metadata.json
qt4_gengui-0.0.1.dist-info/top_level.txt
